infrahub_sync/__init__.py
infrahub_sync/adapters/aci.py
infrahub_sync/adapters/genericrestapi.py
infrahub_sync/adapters/infrahub.py
infrahub_sync/adapters/ipfabricsync.py
infrahub_sync/adapters/nautobot.py
infrahub_sync/adapters/netbox.py
infrahub_sync/adapters/peeringmanager.py
infrahub_sync/adapters/prometheus.py
infrahub_sync/adapters/rest_api_client.py
infrahub_sync/adapters/slurpitsync.py
infrahub_sync/adapters/utils.py
infrahub_sync/cli.py
infrahub_sync/generator/__init__.py
infrahub_sync/generator/templates/diffsync_adapter.j2
infrahub_sync/generator/templates/diffsync_models.j2
infrahub_sync/plugin_loader.py
infrahub_sync/potenda/__init__.py
infrahub_sync/utils.py
infrahub_sync-1.5.0.dist-info/LICENSE.txt
infrahub_sync-1.5.0.dist-info/METADATA
infrahub_sync-1.5.0.dist-info/WHEEL
infrahub_sync-1.5.0.dist-info/entry_points.txt
infrahub_sync-1.5.0.dist-info/RECORD
