Metadata-Version: 2.3
Name: infrahub-sync
Version: 1.5.0
Summary: Infrahub-Sync is a versatile Python package that synchronizes data between a source and a destination system
License: Apache-2.0
Author: OpsMill
Author-email: info@opsmill.com
Requires-Python: >=3.9,<3.13
Classifier: Intended Audience :: Developers
Classifier: License :: OSI Approved :: Apache Software License
Classifier: Programming Language :: Python :: 3
Classifier: Programming Language :: Python :: 3.9
Classifier: Programming Language :: Python :: 3.10
Classifier: Programming Language :: Python :: 3.11
Classifier: Programming Language :: Python :: 3.12
Requires-Dist: diffsync[redis] (>=1.10)
Requires-Dist: infrahub-sdk[all] (>=1,<2)
Requires-Dist: netutils (>=1.9)
Requires-Dist: structlog (>=22.3,<26.0)
Requires-Dist: tqdm (>=4.66)
Project-URL: Documentation, https://docs.infrahub.app/integrations/sync/
Project-URL: Homepage, https://opsmill.com
Project-URL: Repository, https://github.com/opsmill/infrahub
